_quicked
_spglib
quantipy
