Metadata-Version: 1.0
Name: QuantiPy
Version: 0.0.0.dev3
Summary: Python Framework for Quantum Many-Body Computations
Home-page: UNKNOWN
Author: Alexander Wietek, Michael Schuler
Author-email: alexander.wietek@uibk.ac.at
License: GNU GENERAL PUBLIC LICENSE Version 3, 29 June 2007
Platform: UNKNOWN
